LICENSE
MANIFEST.in
README.md
subfind3r.py
Subfind3r.egg-info/PKG-INFO
Subfind3r.egg-info/SOURCES.txt
Subfind3r.egg-info/dependency_links.txt
Subfind3r.egg-info/entry_points.txt
Subfind3r.egg-info/requires.txt
Subfind3r.egg-info/top_level.txt
subbrute/__init__.py
subbrute/names.txt
subbrute/resolvers.txt
subbrute/subbrute.py
Subfind3r-1.3.dist-info/LICENSE
Subfind3r-1.3.dist-info/METADATA
Subfind3r-1.3.dist-info/WHEEL
Subfind3r-1.3.dist-info/entry_points.txt
Subfind3r-1.3.dist-info/top_level.txt
Subfind3r-1.3.dist-info/RECORD
